Workbook

Sheet START
A1: Receipt Shoebox — Expense Capture Kit
A2: Capture receipts as they arrive, then see each quarter's totals in one place. Everything stays on your device — no cloud, no subscription, no uploads.
A4: How to use
A5: Set the year on the QUARTER-SUMMARY sheet (cell B1).
A6: Add each receipt to the RECEIPT-LOG: date, vendor, category, amount, tax, payment method, and the photo/file name.
A7: Keep the photo in one folder; write its file name in the Receipt File column so you can find it later.
A8: Check QUARTER-SUMMARY and YEAR-DASHBOARD — totals update automatically.
A9: At quarter end, filter the log by date and export/print it for your records or your accountant.
A11: Privacy: this workbook never uploads anything. Your receipts and file names stay on your own device.
A12: One currency per workbook. If you pay in several currencies, convert to your main currency before entering the amount.

Sheet CATEGORIES
A1: Category | B1: Description
A2: Office Supplies | B2: paper, pens, printer ink
A3: Software & Subscriptions | B3: apps, cloud tools, licences
A4: Travel & Transport | B4: taxi, fuel, train, flights
A5: Meals & Client Meetings | B5: coffee, lunch with a client
A6: Equipment & Hardware | B6: laptop, monitor, cables
A7: Phone & Internet | B7: mobile bill, broadband
A8: Professional Services | B8: accountant, lawyer, consultant
A9: Marketing & Advertising | B9: ads, flyers, domain
A10: Education & Training | B10: course, book, workshop
A11: Other | B11: anything that fits no other category

Sheet RECEIPT-LOG
A1: Date | B1: Vendor | C1: Category | D1: Description | E1: Amount | F1: Tax | G1: Payment Method | H1: Client / Project | I1: Receipt File | J1: Notes
A2: 46205 | B2: City Office Store | C2: Office Supplies | D2: Printer paper + pens | E2: 24.5 | F2: 2.04 | G2: Card | H2: General | I2: 2026-07-02_city-office-store.jpg
A3: 46209 | B3: CloudDocs | C3: Software & Subscriptions | D3: Cloud storage monthly | E3: 12 | F3: 0 | G3: Card | H3: General | I3: 2026-07-06_clouddocs.png
A4: 46211 | B4: Metro Taxi | C4: Travel & Transport | D4: Taxi to client meeting | E4: 18.75 | F4: 1.56 | G4: Cash | H4: Client: Northwind | I4: 2026-07-08_metro-taxi.jpg
A5: 46213 | B5: Corner Café | C5: Meals & Client Meetings | D5: Coffee with client | E5: 14.2 | F5: 1.18 | G5: Card | H5: Client: Northwind | I5: 2026-07-10_corner-cafe.jpg
A6: 46217 | B6: TechMart | C6: Equipment & Hardware | D6: USB-C cable + mouse | E6: 42.99 | F6: 3.58 | G6: Card | H6: General | I6: 2026-07-14_techmart.jpg
A7: 46218 | B7: MobileCo | C7: Phone & Internet | D7: Mobile bill July | E7: 35 | F7: 2.92 | G7: Bank Transfer | H7: General | I7: 2026-07-15_mobileco.pdf
A8: 46224 | B8: CoWork Hub | C8: Other | D8: Day pass | E8: 19 | F8: 1.58 | G8: Card | H8: General | I8: 2026-07-21_cowork-hub.jpg
A9: 46231 | B9: Freelance Tax Pro | C9: Professional Services | D9: Q2 tax consultation | E9: 120 | F9: 0 | G9: Bank Transfer | H9: General | I9: 2026-07-28_taxpro.pdf
A10: 46237 | B10: AdPlatform | C10: Marketing & Advertising | D10: Social ads — August | E10: 60 | F10: 5 | G10: Card | H10: General | I10: 2026-08-03_adplatform.png
A11: 46239 | B11: SkillUp Courses | C11: Education & Training | D11: Online course: pricing | E11: 89 | F11: 0 | G11: Card | H11: General | I11: 2026-08-05_skillup.pdf
A12: 46245 | B12: BookWorld | C12: Education & Training | D12: Book: freelancing finance | E12: 21.5 | F12: 0 | G12: Card | H12: General | I12: 2026-08-11_bookworld.jpg
A13: 46246 | B13: RailGo | C13: Travel & Transport | D13: Train to client city | E13: 46 | F13: 3.83 | G13: Card | H13: Client: Northwind | I13: 2026-08-12_railgo.pdf
... A21: 46287 | B21: PromoPrint | C21: Marketing & Advertising | D21: Flyers for local fair | E21: 44 | F21: 3.67 | G21: Card | H21: General | I21: 2026-09-22_promoprint.jpg
A202: Total | C202: =COUNTA(A2:A201) | E202: =SUM(E2:E201) | F202: =SUM(F2:F201)

Sheet QUARTER-SUMMARY
A1: Year | B1: 2026
A3: Quarter | B3: Receipts | C3: Total Amount | D3: Total Tax | E3: Office Supplies | F3: Software & Subscriptions | G3: Travel & Transport | H3: Meals & Client Meetings | I3: Equipment & Hardware | J3: Phone & Internet | K3: Professional Services | L3: Marketing & Advertising | M3: Education & Training | N3: Other
A4: Q1 | B4: =COUNTIFS('RECEIPT-LOG'!$A$2:$A$201,">="&DATE($B$1,1,1),'RECEIPT-LOG'!$A$2:$A$201,"<="&DATE($B$1,3,31)) | C4: =SUMIFS('RECEIPT-LOG'!$E$2:$E$201,'RECEIPT-LOG'!$A$2:$A$201,">="&DATE($B$1,1,1),'RECEIPT-LOG'!$A$2:$A$201,"<="&DATE($B$1,3,31)) | D4: =SUMIFS('RECEIPT-LOG'!$F$2:$F$201,'RECEIPT-LOG'!$A$2:$A$201,">="&DATE($B$1,1,1),'RECEIPT-LOG'!$A$2:$A$201,"<="&DATE($B$1,3,31)) | E4: =SUMIFS('RECEIPT-LOG'!$E$2:$E$201,'RECEIPT-LOG'!$A$2:$A$201,">="&DATE($B$1,1,1),'RECEIPT-LOG'!$A$2:$A$201,"<="&DATE($B$1,3,31),'RECEIPT-LOG'!$C$2:$C$201,E$3) | F4: =SUMIFS('RECEIPT-LOG'!$E$2:$E$201,'RECEIPT-LOG'!$A$2:$A$201,">="&DATE($B$1,1,1),'RECEIPT-LOG'!$A$2:$A$201,"<="&DATE($B$1,3,31),'RECEIPT-LOG'!$C$2:$C$201,F$3) | G4: =SUMIFS('RECEIPT-LOG'!$E$2:$E$201,'RECEIPT-LOG'!$A$2:$A$201,">="&DATE($B$1,1,1),'RECEIPT-LOG'!$A$2:$A$201,"<="&DATE($B$1,3,31),'RECEIPT-LOG'!$C$2:$C$201,G$3) | H4: =SUMIFS('RECEIPT-LOG'!$E$2:$E$201,'RECEIPT-LOG'!$A$2:$A$201,">="&DATE($B$1,1,1),'RECEIPT-LOG'!$A$2:$A$201,"<="&DATE($B$1,3,31),'RECEIPT-LOG'!$C$2:$C$201,H$3) | I4: =SUMIFS('RECEIPT-LOG'!$E$2:$E$201,'RECEIPT-LOG'!$A$2:$A$201,">="&DATE($B$1,1,1),'RECEIPT-LOG'!$A$2:$A$201,"<="&DATE($B$1,3,31),'RECEIPT-LOG'!$C$2:$C$201,I$3) | J4: =SUMIFS('RECEIPT-LOG'!$E$2:$E$201,'RECEIPT-LOG'!$A$2:$A$201,">="&DATE($B$1,1,1),'RECEIPT-LOG'!$A$2:$A$201,"<="&DATE($B$1,3,31),'RECEIPT-LOG'!$C$2:$C$201,J$3) | K4: =SUMIFS('RECEIPT-LOG'!$E$2:$E$201,'RECEIPT-LOG'!$A$2:$A$201,">="&DATE($B$1,1,1),'RECEIPT-LOG'!$A$2:$A$201,"<="&DATE($B$1,3,31),'RECEIPT-LOG'!$C$2:$C$201,K$3) | L4: =SUMIFS('RECEIPT-LOG'!$E$2:$E$201,'RECEIPT-LOG'!$A$2:$A$201,">="&DATE($B$1,1,1),'RECEIPT-LOG'!$A$2:$A$201,"<="&DATE($B$1,3,31),'RECEIPT-LOG'!$C$2:$C$201,L$3) | ... N4: =SUMIFS('RECEIPT-LOG'!$E$2:$E$201,'RECEIPT-LOG'!$A$2:$A$201,">="&DATE($B$1,1,1),'RECEIPT-LOG'!$A$2:$A$201,"<="&DATE($B$1,3,31),'RECEIPT-LOG'!$C$2:$C$201,N$3)
A5: Q2 | B5: =COUNTIFS('RECEIPT-LOG'!$A$2:$A$201,">="&DATE($B$1,4,1),'RECEIPT-LOG'!$A$2:$A$201,"<="&DATE($B$1,6,30)) | C5: =SUMIFS('RECEIPT-LOG'!$E$2:$E$201,'RECEIPT-LOG'!$A$2:$A$201,">="&DATE($B$1,4,1),'RECEIPT-LOG'!$A$2:$A$201,"<="&DATE($B$1,6,30)) | D5: =SUMIFS('RECEIPT-LOG'!$F$2:$F$201,'RECEIPT-LOG'!$A$2:$A$201,">="&DATE($B$1,4,1),'RECEIPT-LOG'!$A$2:$A$201,"<="&DATE($B$1,6,30)) | E5: =SUMIFS('RECEIPT-LOG'!$E$2:$E$201,'RECEIPT-LOG'!$A$2:$A$201,">="&DATE($B$1,4,1),'RECEIPT-LOG'!$A$2:$A$201,"<="&DATE($B$1,6,30),'RECEIPT-LOG'!$C$2:$C$201,E$3) | F5: =SUMIFS('RECEIPT-LOG'!$E$2:$E$201,'RECEIPT-LOG'!$A$2:$A$201,">="&DATE($B$1,4,1),'RECEIPT-LOG'!$A$2:$A$201,"<="&DATE($B$1,6,30),'RECEIPT-LOG'!$C$2:$C$201,F$3) | G5: =SUMIFS('RECEIPT-LOG'!$E$2:$E$201,'RECEIPT-LOG'!$A$2:$A$201,">="&DATE($B$1,4,1),'RECEIPT-LOG'!$A$2:$A$201,"<="&DATE($B$1,6,30),'RECEIPT-LOG'!$C$2:$C$201,G$3) | H5: =SUMIFS('RECEIPT-LOG'!$E$2:$E$201,'RECEIPT-LOG'!$A$2:$A$201,">="&DATE($B$1,4,1),'RECEIPT-LOG'!$A$2:$A$201,"<="&DATE($B$1,6,30),'RECEIPT-LOG'!$C$2:$C$201,H$3) | I5: =SUMIFS('RECEIPT-LOG'!$E$2:$E$201,'RECEIPT-LOG'!$A$2:$A$201,">="&DATE($B$1,4,1),'RECEIPT-LOG'!$A$2:$A$201,"<="&DATE($B$1,6,30),'RECEIPT-LOG'!$C$2:$C$201,I$3) | J5: =SUMIFS('RECEIPT-LOG'!$E$2:$E$201,'RECEIPT-LOG'!$A$2:$A$201,">="&DATE($B$1,4,1),'RECEIPT-LOG'!$A$2:$A$201,"<="&DATE($B$1,6,30),'RECEIPT-LOG'!$C$2:$C$201,J$3) | K5: =SUMIFS('RECEIPT-LOG'!$E$2:$E$201,'RECEIPT-LOG'!$A$2:$A$201,">="&DATE($B$1,4,1),'RECEIPT-LOG'!$A$2:$A$201,"<="&DATE($B$1,6,30),'RECEIPT-LOG'!$C$2:$C$201,K$3) | L5: =SUMIFS('RECEIPT-LOG'!$E$2:$E$201,'RECEIPT-LOG'!$A$2:$A$201,">="&DATE($B$1,4,1),'RECEIPT-LOG'!$A$2:$A$201,"<="&DATE($B$1,6,30),'RECEIPT-LOG'!$C$2:$C$201,L$3) | ... N5: =SUMIFS('RECEIPT-LOG'!$E$2:$E$201,'RECEIPT-LOG'!$A$2:$A$201,">="&DATE($B$1,4,1),'RECEIPT-LOG'!$A$2:$A$201,"<="&DATE($B$1,6,30),'RECEIPT-LOG'!$C$2:$C$201,N$3)
A6: Q3 | B6: =COUNTIFS('RECEIPT-LOG'!$A$2:$A$201,">="&DATE($B$1,7,1),'RECEIPT-LOG'!$A$2:$A$201,"<="&DATE($B$1,9,30)) | C6: =SUMIFS('RECEIPT-LOG'!$E$2:$E$201,'RECEIPT-LOG'!$A$2:$A$201,">="&DATE($B$1,7,1),'RECEIPT-LOG'!$A$2:$A$201,"<="&DATE($B$1,9,30)) | D6: =SUMIFS('RECEIPT-LOG'!$F$2:$F$201,'RECEIPT-LOG'!$A$2:$A$201,">="&DATE($B$1,7,1),'RECEIPT-LOG'!$A$2:$A$201,"<="&DATE($B$1,9,30)) | E6: =SUMIFS('RECEIPT-LOG'!$E$2:$E$201,'RECEIPT-LOG'!$A$2:$A$201,">="&DATE($B$1,7,1),'RECEIPT-LOG'!$A$2:$A$201,"<="&DATE($B$1,9,30),'RECEIPT-LOG'!$C$2:$C$201,E$3) | F6: =SUMIFS('RECEIPT-LOG'!$E$2:$E$201,'RECEIPT-LOG'!$A$2:$A$201,">="&DATE($B$1,7,1),'RECEIPT-LOG'!$A$2:$A$201,"<="&DATE($B$1,9,30),'RECEIPT-LOG'!$C$2:$C$201,F$3) | G6: =SUMIFS('RECEIPT-LOG'!$E$2:$E$201,'RECEIPT-LOG'!$A$2:$A$201,">="&DATE($B$1,7,1),'RECEIPT-LOG'!$A$2:$A$201,"<="&DATE($B$1,9,30),'RECEIPT-LOG'!$C$2:$C$201,G$3) | H6: =SUMIFS('RECEIPT-LOG'!$E$2:$E$201,'RECEIPT-LOG'!$A$2:$A$201,">="&DATE($B$1,7,1),'RECEIPT-LOG'!$A$2:$A$201,"<="&DATE($B$1,9,30),'RECEIPT-LOG'!$C$2:$C$201,H$3) | I6: =SUMIFS('RECEIPT-LOG'!$E$2:$E$201,'RECEIPT-LOG'!$A$2:$A$201,">="&DATE($B$1,7,1),'RECEIPT-LOG'!$A$2:$A$201,"<="&DATE($B$1,9,30),'RECEIPT-LOG'!$C$2:$C$201,I$3) | J6: =SUMIFS('RECEIPT-LOG'!$E$2:$E$201,'RECEIPT-LOG'!$A$2:$A$201,">="&DATE($B$1,7,1),'RECEIPT-LOG'!$A$2:$A$201,"<="&DATE($B$1,9,30),'RECEIPT-LOG'!$C$2:$C$201,J$3) | K6: =SUMIFS('RECEIPT-LOG'!$E$2:$E$201,'RECEIPT-LOG'!$A$2:$A$201,">="&DATE($B$1,7,1),'RECEIPT-LOG'!$A$2:$A$201,"<="&DATE($B$1,9,30),'RECEIPT-LOG'!$C$2:$C$201,K$3) | L6: =SUMIFS('RECEIPT-LOG'!$E$2:$E$201,'RECEIPT-LOG'!$A$2:$A$201,">="&DATE($B$1,7,1),'RECEIPT-LOG'!$A$2:$A$201,"<="&DATE($B$1,9,30),'RECEIPT-LOG'!$C$2:$C$201,L$3) | ... N6: =SUMIFS('RECEIPT-LOG'!$E$2:$E$201,'RECEIPT-LOG'!$A$2:$A$201,">="&DATE($B$1,7,1),'RECEIPT-LOG'!$A$2:$A$201,"<="&DATE($B$1,9,30),'RECEIPT-LOG'!$C$2:$C$201,N$3)
A7: Q4 | B7: =COUNTIFS('RECEIPT-LOG'!$A$2:$A$201,">="&DATE($B$1,10,1),'RECEIPT-LOG'!$A$2:$A$201,"<="&DATE($B$1,12,31)) | C7: =SUMIFS('RECEIPT-LOG'!$E$2:$E$201,'RECEIPT-LOG'!$A$2:$A$201,">="&DATE($B$1,10,1),'RECEIPT-LOG'!$A$2:$A$201,"<="&DATE($B$1,12,31)) | D7: =SUMIFS('RECEIPT-LOG'!$F$2:$F$201,'RECEIPT-LOG'!$A$2:$A$201,">="&DATE($B$1,10,1),'RECEIPT-LOG'!$A$2:$A$201,"<="&DATE($B$1,12,31)) | E7: =SUMIFS('RECEIPT-LOG'!$E$2:$E$201,'RECEIPT-LOG'!$A$2:$A$201,">="&DATE($B$1,10,1),'RECEIPT-LOG'!$A$2:$A$201,"<="&DATE($B$1,12,31),'RECEIPT-LOG'!$C$2:$C$201,E$3) | F7: =SUMIFS('RECEIPT-LOG'!$E$2:$E$201,'RECEIPT-LOG'!$A$2:$A$201,">="&DATE($B$1,10,1),'RECEIPT-LOG'!$A$2:$A$201,"<="&DATE($B$1,12,31),'RECEIPT-LOG'!$C$2:$C$201,F$3) | G7: =SUMIFS('RECEIPT-LOG'!$E$2:$E$201,'RECEIPT-LOG'!$A$2:$A$201,">="&DATE($B$1,10,1),'RECEIPT-LOG'!$A$2:$A$201,"<="&DATE($B$1,12,31),'RECEIPT-LOG'!$C$2:$C$201,G$3) | H7: =SUMIFS('RECEIPT-LOG'!$E$2:$E$201,'RECEIPT-LOG'!$A$2:$A$201,">="&DATE($B$1,10,1),'RECEIPT-LOG'!$A$2:$A$201,"<="&DATE($B$1,12,31),'RECEIPT-LOG'!$C$2:$C$201,H$3) | I7: =SUMIFS('RECEIPT-LOG'!$E$2:$E$201,'RECEIPT-LOG'!$A$2:$A$201,">="&DATE($B$1,10,1),'RECEIPT-LOG'!$A$2:$A$201,"<="&DATE($B$1,12,31),'RECEIPT-LOG'!$C$2:$C$201,I$3) | J7: =SUMIFS('RECEIPT-LOG'!$E$2:$E$201,'RECEIPT-LOG'!$A$2:$A$201,">="&DATE($B$1,10,1),'RECEIPT-LOG'!$A$2:$A$201,"<="&DATE($B$1,12,31),'RECEIPT-LOG'!$C$2:$C$201,J$3) | K7: =SUMIFS('RECEIPT-LOG'!$E$2:$E$201,'RECEIPT-LOG'!$A$2:$A$201,">="&DATE($B$1,10,1),'RECEIPT-LOG'!$A$2:$A$201,"<="&DATE($B$1,12,31),'RECEIPT-LOG'!$C$2:$C$201,K$3) | L7: =SUMIFS('RECEIPT-LOG'!$E$2:$E$201,'RECEIPT-LOG'!$A$2:$A$201,">="&DATE($B$1,10,1),'RECEIPT-LOG'!$A$2:$A$201,"<="&DATE($B$1,12,31),'RECEIPT-LOG'!$C$2:$C$201,L$3) | ... N7: =SUMIFS('RECEIPT-LOG'!$E$2:$E$201,'RECEIPT-LOG'!$A$2:$A$201,">="&DATE($B$1,10,1),'RECEIPT-LOG'!$A$2:$A$201,"<="&DATE($B$1,12,31),'RECEIPT-LOG'!$C$2:$C$201,N$3)
A8: Total | B8: =SUM(B4:B7) | C8: =SUM(C4:C7) | D8: =SUM(D4:D7) | E8: =SUM(E4:E7) | F8: =SUM(F4:F7) | G8: =SUM(G4:G7) | H8: =SUM(H4:H7) | I8: =SUM(I4:I7) | ... N8: =SUM(N4:N7)

Sheet YEAR-DASHBOARD
A1: Year | B1: ='QUARTER-SUMMARY'!B1
A3: Category | B3: Annual Total | C3: Receipts
A4: Office Supplies | B4: =SUMIFS('RECEIPT-LOG'!$E$2:$E$201,'RECEIPT-LOG'!$A$2:$A$201,">="&DATE($B$1,1,1),'RECEIPT-LOG'!$A$2:$A$201,"<="&DATE($B$1,12,31),'RECEIPT-LOG'!$C$2:$C$201,$A4) | C4: =COUNTIFS('RECEIPT-LOG'!$A$2:$A$201,">="&DATE($B$1,1,1),'RECEIPT-LOG'!$A$2:$A$201,"<="&DATE($B$1,12,31),'RECEIPT-LOG'!$C$2:$C$201,$A4)
A5: Software & Subscriptions | B5: =SUMIFS('RECEIPT-LOG'!$E$2:$E$201,'RECEIPT-LOG'!$A$2:$A$201,">="&DATE($B$1,1,1),'RECEIPT-LOG'!$A$2:$A$201,"<="&DATE($B$1,12,31),'RECEIPT-LOG'!$C$2:$C$201,$A5) | C5: =COUNTIFS('RECEIPT-LOG'!$A$2:$A$201,">="&DATE($B$1,1,1),'RECEIPT-LOG'!$A$2:$A$201,"<="&DATE($B$1,12,31),'RECEIPT-LOG'!$C$2:$C$201,$A5)
A6: Travel & Transport | B6: =SUMIFS('RECEIPT-LOG'!$E$2:$E$201,'RECEIPT-LOG'!$A$2:$A$201,">="&DATE($B$1,1,1),'RECEIPT-LOG'!$A$2:$A$201,"<="&DATE($B$1,12,31),'RECEIPT-LOG'!$C$2:$C$201,$A6) | C6: =COUNTIFS('RECEIPT-LOG'!$A$2:$A$201,">="&DATE($B$1,1,1),'RECEIPT-LOG'!$A$2:$A$201,"<="&DATE($B$1,12,31),'RECEIPT-LOG'!$C$2:$C$201,$A6)
A7: Meals & Client Meetings | B7: =SUMIFS('RECEIPT-LOG'!$E$2:$E$201,'RECEIPT-LOG'!$A$2:$A$201,">="&DATE($B$1,1,1),'RECEIPT-LOG'!$A$2:$A$201,"<="&DATE($B$1,12,31),'RECEIPT-LOG'!$C$2:$C$201,$A7) | C7: =COUNTIFS('RECEIPT-LOG'!$A$2:$A$201,">="&DATE($B$1,1,1),'RECEIPT-LOG'!$A$2:$A$201,"<="&DATE($B$1,12,31),'RECEIPT-LOG'!$C$2:$C$201,$A7)
A8: Equipment & Hardware | B8: =SUMIFS('RECEIPT-LOG'!$E$2:$E$201,'RECEIPT-LOG'!$A$2:$A$201,">="&DATE($B$1,1,1),'RECEIPT-LOG'!$A$2:$A$201,"<="&DATE($B$1,12,31),'RECEIPT-LOG'!$C$2:$C$201,$A8) | C8: =COUNTIFS('RECEIPT-LOG'!$A$2:$A$201,">="&DATE($B$1,1,1),'RECEIPT-LOG'!$A$2:$A$201,"<="&DATE($B$1,12,31),'RECEIPT-LOG'!$C$2:$C$201,$A8)
A9: Phone & Internet | B9: =SUMIFS('RECEIPT-LOG'!$E$2:$E$201,'RECEIPT-LOG'!$A$2:$A$201,">="&DATE($B$1,1,1),'RECEIPT-LOG'!$A$2:$A$201,"<="&DATE($B$1,12,31),'RECEIPT-LOG'!$C$2:$C$201,$A9) | C9: =COUNTIFS('RECEIPT-LOG'!$A$2:$A$201,">="&DATE($B$1,1,1),'RECEIPT-LOG'!$A$2:$A$201,"<="&DATE($B$1,12,31),'RECEIPT-LOG'!$C$2:$C$201,$A9)
A10: Professional Services | B10: =SUMIFS('RECEIPT-LOG'!$E$2:$E$201,'RECEIPT-LOG'!$A$2:$A$201,">="&DATE($B$1,1,1),'RECEIPT-LOG'!$A$2:$A$201,"<="&DATE($B$1,12,31),'RECEIPT-LOG'!$C$2:$C$201,$A10) | C10: =COUNTIFS('RECEIPT-LOG'!$A$2:$A$201,">="&DATE($B$1,1,1),'RECEIPT-LOG'!$A$2:$A$201,"<="&DATE($B$1,12,31),'RECEIPT-LOG'!$C$2:$C$201,$A10)
A11: Marketing & Advertising | B11: =SUMIFS('RECEIPT-LOG'!$E$2:$E$201,'RECEIPT-LOG'!$A$2:$A$201,">="&DATE($B$1,1,1),'RECEIPT-LOG'!$A$2:$A$201,"<="&DATE($B$1,12,31),'RECEIPT-LOG'!$C$2:$C$201,$A11) | C11: =COUNTIFS('RECEIPT-LOG'!$A$2:$A$201,">="&DATE($B$1,1,1),'RECEIPT-LOG'!$A$2:$A$201,"<="&DATE($B$1,12,31),'RECEIPT-LOG'!$C$2:$C$201,$A11)
A12: Education & Training | B12: =SUMIFS('RECEIPT-LOG'!$E$2:$E$201,'RECEIPT-LOG'!$A$2:$A$201,">="&DATE($B$1,1,1),'RECEIPT-LOG'!$A$2:$A$201,"<="&DATE($B$1,12,31),'RECEIPT-LOG'!$C$2:$C$201,$A12) | C12: =COUNTIFS('RECEIPT-LOG'!$A$2:$A$201,">="&DATE($B$1,1,1),'RECEIPT-LOG'!$A$2:$A$201,"<="&DATE($B$1,12,31),'RECEIPT-LOG'!$C$2:$C$201,$A12)
A13: Other | B13: =SUMIFS('RECEIPT-LOG'!$E$2:$E$201,'RECEIPT-LOG'!$A$2:$A$201,">="&DATE($B$1,1,1),'RECEIPT-LOG'!$A$2:$A$201,"<="&DATE($B$1,12,31),'RECEIPT-LOG'!$C$2:$C$201,$A13) | C13: =COUNTIFS('RECEIPT-LOG'!$A$2:$A$201,">="&DATE($B$1,1,1),'RECEIPT-LOG'!$A$2:$A$201,"<="&DATE($B$1,12,31),'RECEIPT-LOG'!$C$2:$C$201,$A13)
A14: Total | B14: =SUM(B4:B13) | C14: =SUM(C4:C13)
A16: Receipts | B16: ='QUARTER-SUMMARY'!B8
A17: Total Amount | B17: ='QUARTER-SUMMARY'!C8
A18: Total Tax | B18: ='QUARTER-SUMMARY'!D8
A19: Average Receipt | B19: =IF(B16=0,0,B17/B16)
A20: Largest Receipt | B20: =MAX('RECEIPT-LOG'!E2:E201)
A21: Receipts with File | B21: =COUNTIF('RECEIPT-LOG'!I2:I201,"<>")
A22: Receipts Missing File | B22: =B16-B21
